_base.so
_control.so
_geometric.so
_tools.so
_util.so
libompl.so
libompl.so.1.7.0
libompl.so.18
ompl/__init__.py
ompl/base/__init__.py
ompl/base/_base.so
ompl/control/__init__.py
ompl/control/_control.so
ompl/geometric/__init__.py
ompl/geometric/_geometric.so
ompl/tools/__init__.py
ompl/tools/_tools.so
ompl/util/__init__.py
ompl/util/_util.so
ompl.libs/libboost_atomic-14645d8c.so.1.87.0
ompl.libs/libboost_container-c6b946a2.so.1.87.0
ompl.libs/libboost_filesystem-264da5f0.so.1.87.0
ompl.libs/libboost_graph-6c427e27.so.1.87.0
ompl.libs/libboost_numpy310-b6bce5d4.so.1.87.0
ompl.libs/libboost_python310-1d3937a7.so.1.87.0
ompl.libs/libboost_serialization-d3ad8370.so.1.87.0
ompl.libs/libboost_system-eb5a03f4.so.1.87.0
ompl.libs/libompl-c05b17ef.so.1.7.0
ompl-1.7.0.dist-info/METADATA
ompl-1.7.0.dist-info/WHEEL
ompl-1.7.0.dist-info/top_level.txt
ompl-1.7.0.dist-info/RECORD
